odoo/addons/stock_release_channel_partner_by_date/README.rst
odoo/addons/stock_release_channel_partner_by_date/__init__.py
odoo/addons/stock_release_channel_partner_by_date/__manifest__.py
odoo/addons/stock_release_channel_partner_by_date/i18n/it.po
odoo/addons/stock_release_channel_partner_by_date/i18n/stock_release_channel_partner_by_date.pot
odoo/addons/stock_release_channel_partner_by_date/models/__init__.py
odoo/addons/stock_release_channel_partner_by_date/models/res_partner.py
odoo/addons/stock_release_channel_partner_by_date/models/stock_picking.py
odoo/addons/stock_release_channel_partner_by_date/models/stock_release_channel.py
odoo/addons/stock_release_channel_partner_by_date/models/stock_release_channel_partner_date.py
odoo/addons/stock_release_channel_partner_by_date/readme/CONTRIBUTORS.rst
odoo/addons/stock_release_channel_partner_by_date/readme/DESCRIPTION.rst
odoo/addons/stock_release_channel_partner_by_date/security/stock_release_channel_partner_date.xml
odoo/addons/stock_release_channel_partner_by_date/static/description/icon.png
odoo/addons/stock_release_channel_partner_by_date/static/description/index.html
odoo/addons/stock_release_channel_partner_by_date/tests/__init__.py
odoo/addons/stock_release_channel_partner_by_date/tests/common.py
odoo/addons/stock_release_channel_partner_by_date/tests/test_release_channel_partner_date.py
odoo/addons/stock_release_channel_partner_by_date/views/res_partner.xml
odoo_addon_stock_release_channel_partner_by_date-16.0.2.0.1.dist-info/METADATA
odoo_addon_stock_release_channel_partner_by_date-16.0.2.0.1.dist-info/WHEEL
odoo_addon_stock_release_channel_partner_by_date-16.0.2.0.1.dist-info/top_level.txt
odoo_addon_stock_release_channel_partner_by_date-16.0.2.0.1.dist-info/RECORD
